ukt/__init__.py
ukt/client.py
ukt/containers.py
ukt/embedded.py
ukt/exceptions.py
ukt/queue.py
ukt/replication.py
ukt/serializer.c
ukt/serializer.cpython-39-x86_64-linux-gnu.so
ukt/serializer.pyx
ukt/tests.py
ukt/scripts/__init__.py
ukt/scripts/kt.lua
ukt-0.4.7.dist-info/METADATA
ukt-0.4.7.dist-info/WHEEL
ukt-0.4.7.dist-info/top_level.txt
ukt-0.4.7.dist-info/RECORD
ukt-0.4.7.dist-info/licenses/LICENSE
