Metadata-Version: 2.4
Name: ukt
Version: 0.4.7
Summary: fast, full-featured kyototycoon client
Author-email: Charles Leifer <coleifer@gmail.com>
License: Copyright (c) 2010 Charles Leifer
Project-URL: Repository, https://github.com/coleifer/ukt
Project-URL: Documentation, https://ukt.readthedocs.io/
Classifier: Programming Language :: Python :: 2
Classifier: Programming Language :: Python :: 3
Classifier: Topic :: Software Development :: Libraries :: Python Modules
License-File: LICENSE
Dynamic: license-file
